.gitignore
.travis.yml
CHANGELOG.md
LICENSE.mit
README.md
setup.cfg
setup.py
compressor_toolkit/__init__.py
compressor_toolkit/apps.py
compressor_toolkit/precompilers.py
django_compressor_toolkit.egg-info/PKG-INFO
django_compressor_toolkit.egg-info/SOURCES.txt
django_compressor_toolkit.egg-info/dependency_links.txt
django_compressor_toolkit.egg-info/requires.txt
django_compressor_toolkit.egg-info/top_level.txt
tests/conftest.py
tests/integration_tests/test_views.py
tests/test_project/manage.py
tests/test_project/test_project/__init__.py
tests/test_project/test_project/settings.py
tests/test_project/test_project/urls.py
tests/test_project/test_project/app/__init__.py
tests/test_project/test_project/app/static/app/layout.scss
tests/test_project/test_project/app/static/app/scripts.js
tests/test_project/test_project/app/templates/app/template-with-es6-file.html
tests/test_project/test_project/app/templates/app/template-with-es6-inline.html
tests/test_project/test_project/app/templates/app/template-with-scss-file.html
tests/test_project/test_project/app/templates/app/template-with-scss-inline.html
tests/test_project/test_project/base/__init__.py
tests/test_project/test_project/base/static/base/framework.js
tests/test_project/test_project/base/static/base/utils.js
tests/test_project/test_project/base/static/base/variables.scss
tests/unit_tests/test_precompilers.py