Metadata-Version: 1.1
Name: django-compressor-toolkit
Version: 0.6.0
Summary: Set of add-ons for django-compressor
Home-page: https://github.com/kottenator/django-compressor-toolkit
Author: Rostyslav Bryzgunov
Author-email: kottenator@gmail.com
License: MIT
Platform: UNKNOWN
Classifier: Framework :: Django
Classifier: Intended Audience :: Developers
Classifier: License :: OSI Approved :: MIT License
Classifier: Operating System :: OS Independent
Classifier: Programming Language :: Python :: 2
Classifier: Programming Language :: Python :: 3
